LICENSE
MANIFEST.in
README.rst
setup.py
cuser/__init__.py
cuser/admin.py
cuser/apps.py
cuser/forms.py
cuser/models.py
cuser/settings.py
cuser/migrations/0001_initial.py
cuser/migrations/__init__.py
cuser/templates/admin/cuser/cuser/add_form.html
django_username_email_fullname.egg-info/PKG-INFO
django_username_email_fullname.egg-info/SOURCES.txt
django_username_email_fullname.egg-info/dependency_links.txt
django_username_email_fullname.egg-info/requires.txt
django_username_email_fullname.egg-info/top_level.txt