Metadata-Version: 1.1
Name: django-username-email-fullname
Version: 2.0.3
Summary: Custom Django User model that makes email the USERNAME_FIELD.
Home-page: https://github.com/hairychris/django-username-email-fullname/
Author: Chris Franklin
Author-email: chris@hairy.io
License: MIT
Keywords: user email username fullname
Platform: UNKNOWN
Classifier: Development Status :: 3 - Alpha
Classifier: Intended Audience :: Developers
Classifier: Topic :: Internet :: WWW/HTTP
Classifier: Topic :: Internet :: WWW/HTTP :: Dynamic Content
Classifier: License :: OSI Approved :: MIT License
Classifier: Programming Language :: Python
Classifier: Programming Language :: Python :: 3.4
Classifier: Environment :: Web Environment
Classifier: Framework :: Django
Classifier: Framework :: Django :: 1.8
Classifier: Framework :: Django :: 1.9
Classifier: Framework :: Django :: 1.10
Classifier: Operating System :: OS Independent
